pyaudiobook/__init__.py
pyaudiobook/audioBook.py
pyaudiobook/utils.py
pyaudiobook-0.0.5.dist-info/LICENSE
pyaudiobook-0.0.5.dist-info/METADATA
pyaudiobook-0.0.5.dist-info/WHEEL
pyaudiobook-0.0.5.dist-info/top_level.txt
pyaudiobook-0.0.5.dist-info/RECORD
