Metadata-Version: 2.1
Name: pyaudiobook
Version: 0.0.5
Summary: pyaudiobook is a python package which converts pdf to mp3 files
Home-page: https://github.com/Rahul-157/AudioBook
Author: Rahul Kumar
Author-email: kum28ra@gmail.com
License: MIT
Platform: UNKNOWN
Classifier: Development Status :: 4 - Beta
Classifier: License :: OSI Approved :: MIT License
Classifier: Programming Language :: Python
Classifier: Programming Language :: Python :: 3.6
Classifier: Topic :: Education
Classifier: Topic :: Multimedia :: Sound/Audio
Classifier: Intended Audience :: Developers
Classifier: Intended Audience :: Education
Classifier: Intended Audience :: End Users/Desktop
Requires-Python: >=3.6
Requires-Dist: gtts
Requires-Dist: pdfminer
